{
  "path": "/mcpar/program-information/add-plans",
  "intro": {
    "section": "Section A: Program Information",
    "subsection": "Add plans (A.7)",
    "info": [
      {
        "type": "text",
        "content": "Enter the name of each plan that participates in the program for which the state is reporting data."
      }
    ]
  },
  "form": {
    "id": "aap",
    "options": {
      "mode": "onChange"
    },
    "fields": [
      {
        "id": "aap-1",
        "type": "dynamic",
        "props": {
          "label": "Plan name"
        }
      }
    ]
  }
}
