{
  "id": "aep",
  "options": {
    "mode": "onChange"
  },
  "fields": [
    {
      "id": "programName",
      "type": "text",
      "validation": "text",
      "props": {
        "label": "Program name"
      }
    },
    {
      "id": "reportingPeriodStartDate",
      "type": "date",
      "validation": "date",
      "props": {
        "label": "A.5a Reporting period (i.e. contract period) start date",
        "hint": "Enter start date of the reporting period represented in the report.",
        "timetype": "startDate"
      }
    },
    {
      "id": "reportingPeriodEndDate",
      "type": "date",
      "validation": {
        "type": "endDate",
        "dependentFieldName": "reportingPeriodStartDate"
      },
      "props": {
        "label": "A.5b Reporting period  (i.e. contract period) end date",
        "hint": "Enter end date of the reporting period represented in the report.",
        "timetype": "endDate"
      }
    },
    {
      "id": "combinedData",
      "type": "checkbox",
      "validation": "checkboxSingle",
      "props": {
        "label": "Exclusion of CHIP from MCPAR",
        "hint": "For Medicaid-only or Medicaid Expansion CHIP programs, select this checkbox if there are reporting items for which the state is unable to remove Separate CHIP information.",
        "choices": [
          {
            "name": "option1",
            "label": "Yes, the report contains items for which the state is unable to remove Separate CHIP information"
          }
        ]
      }
    }
  ]
}
